<?xml version='1.0' encoding='utf-8'?>
<figuras><figura nombre="Tabla Llena 1" fecha="2025-08-23 16:09:13" centro_bloqueado="0"><celda idx="1" color="#ff0037" pos="B1" /><celda idx="2" color="#ff0037" pos="I1" /><celda idx="3" color="#ff0037" pos="N1" /><celda idx="4" color="#ff0037" pos="G1" /><celda idx="5" color="#ff0037" pos="O1" /><celda idx="6" color="#ff0037" pos="B2" /><celda idx="7" color="#ff0037" pos="I2" /><celda idx="8" color="#ff0037" pos="N2" /><celda idx="9" color="#ff0037" pos="G2" /><celda idx="10" color="#ff0037" pos="O2" /><celda idx="11" color="#ff0037" pos="B3" /><celda idx="12" color="#ff0037" pos="I3" /><celda idx="13" color="#ff0037" pos="N3" /><celda idx="14" color="#ff0037" pos="G3" /><celda idx="15" color="#ff0037" pos="O3" /><celda idx="16" color="#ff0037" pos="B4" /><celda idx="17" color="#ff0037" pos="I4" /><celda idx="18" color="#ff0037" pos="N4" /><celda idx="19" color="#ff0037" pos="G4" /><celda idx="20" color="#ff0037" pos="O4" /><celda idx="21" color="#ff0037" pos="B5" /><celda idx="22" color="#ff0037" pos="I5" /><celda idx="23" color="#ff0037" pos="N5" /><celda idx="24" color="#ff0037" pos="G5" /><celda idx="25" color="#ff0037" pos="O5" /></figura><figura nombre="Tabla Llena 2" fecha="2025-08-23 16:09:13" centro_bloqueado="0"><celda idx="1" color="#ff0037" pos="B1" /><celda idx="2" color="#ff0037" pos="I1" /><celda idx="3" color="#ff0037" pos="N1" /><celda idx="4" color="#ff0037" pos="G1" /><celda idx="5" color="#ff0037" pos="O1" /><celda idx="6" color="#ff0037" pos="B2" /><celda idx="7" color="#ff0037" pos="I2" /><celda idx="8" color="#ff0037" pos="N2" /><celda idx="9" color="#ff0037" pos="G2" /><celda idx="10" color="#ff0037" pos="O2" /><celda idx="11" color="#ff0037" pos="B3" /><celda idx="12" color="#ff0037" pos="I3" /><celda idx="13" color="#ff0037" pos="N3" /><celda idx="14" color="#ff0037" pos="G3" /><celda idx="15" color="#ff0037" pos="O3" /><celda idx="16" color="#ff0037" pos="B4" /><celda idx="17" color="#ff0037" pos="I4" /><celda idx="18" color="#ff0037" pos="N4" /><celda idx="19" color="#ff0037" pos="G4" /><celda idx="20" color="#ff0037" pos="O4" /><celda idx="21" color="#ff0037" pos="B5" /><celda idx="22" color="#ff0037" pos="I5" /><celda idx="23" color="#ff0037" pos="N5" /><celda idx="24" color="#ff0037" pos="G5" /><celda idx="25" color="#ff0037" pos="O5" /></figura><figura nombre="5TA LINEA" fecha="2025-08-23 16:09:13" centro_bloqueado="1"><celda idx="1" color="#E8E8E8" pos="B1" /><celda idx="2" color="#E8E8E8" pos="I1" /><celda idx="3" color="#E8E8E8" pos="N1" /><celda idx="4" color="#E8E8E8" pos="G1" /><celda idx="5" color="#E8E8E8" pos="O1" /><celda idx="6" color="#E8E8E8" pos="B2" /><celda idx="7" color="#E8E8E8" pos="I2" /><celda idx="8" color="#E8E8E8" pos="N2" /><celda idx="9" color="#E8E8E8" pos="G2" /><celda idx="10" color="#E8E8E8" pos="O2" /><celda idx="11" color="#E8E8E8" pos="B3" /><celda idx="12" color="#E8E8E8" pos="I3" /><celda idx="13" color="#E8E8E8" pos="N3" /><celda idx="14" color="#E8E8E8" pos="G3" /><celda idx="15" color="#E8E8E8" pos="O3" /><celda idx="16" color="#E8E8E8" pos="B4" /><celda idx="17" color="#E8E8E8" pos="I4" /><celda idx="18" color="#E8E8E8" pos="N4" /><celda idx="19" color="#E8E8E8" pos="G4" /><celda idx="20" color="#E8E8E8" pos="O4" /><celda idx="21" color="#ff0037" pos="B5" /><celda idx="22" color="#ff0037" pos="I5" /><celda idx="23" color="#ff0037" pos="N5" /><celda idx="24" color="#ff0037" pos="G5" /><celda idx="25" color="#ff0037" pos="O5" /></figura><figura nombre="DIAGONAL 1" fecha="2025-08-23 16:09:13" centro_bloqueado="1"><celda idx="1" color="#E8E8E8" pos="B1" /><celda idx="2" color="#E8E8E8" pos="I1" /><celda idx="3" color="#E8E8E8" pos="N1" /><celda idx="4" color="#E8E8E8" pos="G1" /><celda idx="5" color="#ff0037" pos="O1" /><celda idx="6" color="#E8E8E8" pos="B2" /><celda idx="7" color="#E8E8E8" pos="I2" /><celda idx="8" color="#E8E8E8" pos="N2" /><celda idx="9" color="#ff0037" pos="G2" /><celda idx="10" color="#E8E8E8" pos="O2" /><celda idx="11" color="#E8E8E8" pos="B3" /><celda idx="12" color="#E8E8E8" pos="I3" /><celda idx="13" color="#E8E8E8" pos="N3" /><celda idx="14" color="#E8E8E8" pos="G3" /><celda idx="15" color="#E8E8E8" pos="O3" /><celda idx="16" color="#E8E8E8" pos="B4" /><celda idx="17" color="#ff0037" pos="I4" /><celda idx="18" color="#E8E8E8" pos="N4" /><celda idx="19" color="#E8E8E8" pos="G4" /><celda idx="20" color="#E8E8E8" pos="O4" /><celda idx="21" color="#ff0037" pos="B5" /><celda idx="22" color="#E8E8E8" pos="I5" /><celda idx="23" color="#E8E8E8" pos="N5" /><celda idx="24" color="#E8E8E8" pos="G5" /><celda idx="25" color="#E8E8E8" pos="O5" /></figura><figura nombre="ESPADA" fecha="2025-08-23 16:09:13" centro_bloqueado="1"><celda idx="1" color="#E8E8E8" pos="B1" /><celda idx="2" color="#E8E8E8" pos="I1" /><celda idx="3" color="#E8E8E8" pos="N1" /><celda idx="4" color="#E8E8E8" pos="G1" /><celda idx="5" color="#ff0037" pos="O1" /><celda idx="6" color="#E8E8E8" pos="B2" /><celda idx="7" color="#E8E8E8" pos="I2" /><celda idx="8" color="#E8E8E8" pos="N2" /><celda idx="9" color="#ff0037" pos="G2" /><celda idx="10" color="#E8E8E8" pos="O2" /><celda idx="11" color="#ff0037" pos="B3" /><celda idx="12" color="#E8E8E8" pos="I3" /><celda idx="13" color="#E8E8E8" pos="N3" /><celda idx="14" color="#E8E8E8" pos="G3" /><celda idx="15" color="#E8E8E8" pos="O3" /><celda idx="16" color="#E8E8E8" pos="B4" /><celda idx="17" color="#ff0037" pos="I4" /><celda idx="18" color="#E8E8E8" pos="N4" /><celda idx="19" color="#E8E8E8" pos="G4" /><celda idx="20" color="#E8E8E8" pos="O4" /><celda idx="21" color="#ff0037" pos="B5" /><celda idx="22" color="#E8E8E8" pos="I5" /><celda idx="23" color="#ff0037" pos="N5" /><celda idx="24" color="#E8E8E8" pos="G5" /><celda idx="25" color="#E8E8E8" pos="O5" /></figura><figura nombre="HORIZONTAL 1" fecha="2025-08-23 16:09:13" centro_bloqueado="1"><celda idx="1" color="#ff0037" pos="B1" /><celda idx="2" color="#ff0037" pos="I1" /><celda idx="3" color="#ff0037" pos="N1" /><celda idx="4" color="#ff0037" pos="G1" /><celda idx="5" color="#ff0037" pos="O1" /><celda idx="6" color="#E8E8E8" pos="B2" /><celda idx="7" color="#E8E8E8" pos="I2" /><celda idx="8" color="#E8E8E8" pos="N2" /><celda idx="9" color="#E8E8E8" pos="G2" /><celda idx="10" color="#E8E8E8" pos="O2" /><celda idx="11" color="#E8E8E8" pos="B3" /><celda idx="12" color="#E8E8E8" pos="I3" /><celda idx="13" color="#E8E8E8" pos="N3" /><celda idx="14" color="#E8E8E8" pos="G3" /><celda idx="15" color="#E8E8E8" pos="O3" /><celda idx="16" color="#E8E8E8" pos="B4" /><celda idx="17" color="#E8E8E8" pos="I4" /><celda idx="18" color="#E8E8E8" pos="N4" /><celda idx="19" color="#E8E8E8" pos="G4" /><celda idx="20" color="#E8E8E8" pos="O4" /><celda idx="21" color="#E8E8E8" pos="B5" /><celda idx="22" color="#E8E8E8" pos="I5" /><celda idx="23" color="#E8E8E8" pos="N5" /><celda idx="24" color="#E8E8E8" pos="G5" /><celda idx="25" color="#E8E8E8" pos="O5" /></figura></figuras>